Cross_Sectional_Parameter_Calculation/__init__.py
Cross_Sectional_Parameter_Calculation/core.py
Cross_Sectional_Parameter_Calculation/test.py
cross_sectional_parameter_calculation-0.1.6.dist-info/LICENSE.txt
cross_sectional_parameter_calculation-0.1.6.dist-info/METADATA
cross_sectional_parameter_calculation-0.1.6.dist-info/WHEEL
cross_sectional_parameter_calculation-0.1.6.dist-info/top_level.txt
cross_sectional_parameter_calculation-0.1.6.dist-info/RECORD
