Metadata-Version: 2.2
Name: cross_sectional_parameter_calculation
Version: 0.1.6
Summary: 一个用以进行圆环截面参数计算的库，我主要是把它拿来算桩的相关问题
Author: ManiacsTraitor
Author-email: 2727671635@QQ.COM
License: MIT
Requires-Python: >=3.6
License-File: LICENSE.txt
Dynamic: author
Dynamic: author-email
Dynamic: description
Dynamic: description-content-type
Dynamic: license
Dynamic: requires-python
Dynamic: summary
